gmail_digest/__init__.py
gmail_digest/internet.py
gmail_digest/util.py
gmail_digest-1.6.0.dist-info/LICENSE
gmail_digest-1.6.0.dist-info/METADATA
gmail_digest-1.6.0.dist-info/WHEEL
gmail_digest-1.6.0.dist-info/entry_points.txt
gmail_digest-1.6.0.dist-info/RECORD
