Metadata-Version: 2.1
Name: gmail_digest
Version: 1.6.0
Summary: A tool to generate a daily digest of your Gmail inbox. Helpful if you have agents working on your behalf.
Home-page: https://github.com/iloveitaly/gmail-digest
License: MIT
Keywords: gmail,email,gmail-api,llm,ai,digest
Author: Michael Bianco
Author-email: mike@mikebian.co
Requires-Python: >=3.9,<4.0
Classifier: License :: OSI Approved :: MIT License
Classifier: Programming Language :: Python :: 3
Classifier: Programming Language :: Python :: 3.9
Classifier: Programming Language :: Python :: 3.10
Classifier: Programming Language :: Python :: 3.11
Classifier: Programming Language :: Python :: 3.12
Requires-Dist: apscheduler (>=3.10.4,<4.0.0)
Requires-Dist: autoflake (>=2.3.1,<3.0.0)
Requires-Dist: backoff (>=2.2.1,<3.0.0)
Requires-Dist: click (>=8.1.7,<9.0.0)
Requires-Dist: funcy-pipe (>=0.11.1,<0.12.0)
Requires-Dist: google-api-python-client (>=2.142.0,<3.0.0)
Requires-Dist: google-auth-httplib2 (>=0.2.0,<0.3.0)
Requires-Dist: google-auth-oauthlib (>=1.2.1,<2.0.0)
Requires-Dist: markdown (>=3.7,<4.0)
Requires-Dist: openai (>=1.42.0,<2.0.0)
Requires-Dist: python-decouple (>=3.8,<4.0)
Requires-Dist: structlog (>=24.4.0,<25.0.0)
